numin/NuminAPI.py
numin/__init__.py
numin/backtest_wrapper.py
numin/utils/__init__.py
numin/utils/backtest.py
numin/utils/featfuncs.py
numin/utils/feed_env.py
numin/utils/feeds.py
numin/utils/india_calendar.py
numin/utils/scanner.py
numin/utils/synfeed.py
numin-2.0.10.dist-info/METADATA
numin-2.0.10.dist-info/WHEEL
numin-2.0.10.dist-info/top_level.txt
numin-2.0.10.dist-info/RECORD
