Metadata-Version: 2.4
Name: numin
Version: 2.0.10
Summary: numin package
Author-email: Gautam Shroff <gautam.shroff@iiitd.ac.in>
Project-URL: Homepage, https://github.com/pypa/sampleproject
Project-URL: Issues, https://github.com/pypa/sampleproject/issues
Classifier: Programming Language :: Python :: 3
Classifier: License :: OSI Approved :: MIT License
Classifier: Operating System :: OS Independent
Requires-Python: >=3.10
Requires-Dist: anvil_uplink
Requires-Dist: import_ipynb
Requires-Dist: ipython
Requires-Dist: numpy
Requires-Dist: pandas
Requires-Dist: pandas_ta
Requires-Dist: pytz
Requires-Dist: requests
